<?xml version="1.0" encoding="UTF-8"?>
<!DOCTYPE mapper PUBLIC "-//mybatis.org//DTD Mapper 3.0//EN" "http://mybatis.org/dtd/mybatis-3-mapper.dtd">
<mapper namespace="com.bird.dao.SystemRouteMapper">
  <resultMap id="BaseResultMap" type="com.bird.model.entity.SystemRoute">
    <!--
      WARNING - @mbg.generated
      This element is automatically generated by MyBatis Generator, do not modify.
      This element was generated on Wed Nov 13 05:06:51 GMT+08:00 2019.
    -->
    <id column="id" jdbcType="INTEGER" property="id" />
    <result column="path" jdbcType="VARCHAR" property="path" />
    <result column="parent" jdbcType="INTEGER" property="parent" />
    <result column="async" jdbcType="BIT" property="async" />
    <result column="des" jdbcType="VARCHAR" property="des" />
  </resultMap>
  <sql id="Example_Where_Clause">
    <!--
      WARNING - @mbg.generated
      This element is automatically generated by MyBatis Generator, do not modify.
      This element was generated on Wed Nov 13 05:06:51 GMT+08:00 2019.
    -->
    <where>
      <foreach collection="oredCriteria" item="criteria" separator="or">
        <if test="criteria.valid">
          <trim prefix="(" prefixOverrides="and" suffix=")">
            <foreach collection="criteria.criteria" item="criterion">
              <choose>
                <when test="criterion.noValue">
                  and ${criterion.condition}
                </when>
                <when test="criterion.singleValue">
                  and ${criterion.condition} #{criterion.value}
                </when>
                <when test="criterion.betweenValue">
                  and ${criterion.condition} #{criterion.value} and #{criterion.secondValue}
                </when>
                <when test="criterion.listValue">
                  and ${criterion.condition}
                  <foreach close=")" collection="criterion.value" item="listItem" open="(" separator=",">
                    #{listItem}
                  </foreach>
                </when>
              </choose>
            </foreach>
          </trim>
        </if>
      </foreach>
    </where>
  </sql>
  <sql id="Update_By_Example_Where_Clause">
    <!--
      WARNING - @mbg.generated
      This element is automatically generated by MyBatis Generator, do not modify.
      This element was generated on Wed Nov 13 05:06:51 GMT+08:00 2019.
    -->
    <where>
      <foreach collection="example.oredCriteria" item="criteria" separator="or">
        <if test="criteria.valid">
          <trim prefix="(" prefixOverrides="and" suffix=")">
            <foreach collection="criteria.criteria" item="criterion">
              <choose>
                <when test="criterion.noValue">
                  and ${criterion.condition}
                </when>
                <when test="criterion.singleValue">
                  and ${criterion.condition} #{criterion.value}
                </when>
                <when test="criterion.betweenValue">
                  and ${criterion.condition} #{criterion.value} and #{criterion.secondValue}
                </when>
                <when test="criterion.listValue">
                  and ${criterion.condition}
                  <foreach close=")" collection="criterion.value" item="listItem" open="(" separator=",">
                    #{listItem}
                  </foreach>
                </when>
              </choose>
            </foreach>
          </trim>
        </if>
      </foreach>
    </where>
  </sql>
  <sql id="Base_Column_List">
    <!--
      WARNING - @mbg.generated
      This element is automatically generated by MyBatis Generator, do not modify.
      This element was generated on Wed Nov 13 05:06:51 GMT+08:00 2019.
    -->
    id, path, parent, async, des
  </sql>
  <select id="selectByExample" parameterType="com.bird.model.entity.SystemRouteExample" resultMap="BaseResultMap">
    <!--
      WARNING - @mbg.generated
      This element is automatically generated by MyBatis Generator, do not modify.
      This element was generated on Wed Nov 13 05:06:51 GMT+08:00 2019.
    -->
    select
    <if test="distinct">
      distinct
    </if>
    <include refid="Base_Column_List" />
    from T_SYSTEM_ROUTE
    <if test="_parameter != null">
      <include refid="Example_Where_Clause" />
    </if>
    <if test="orderByClause != null">
      order by ${orderByClause}
    </if>
  </select>
  <select id="selectByPrimaryKey" parameterType="java.lang.Integer" resultMap="BaseResultMap">
    <!--
      WARNING - @mbg.generated
      This element is automatically generated by MyBatis Generator, do not modify.
      This element was generated on Wed Nov 13 05:06:51 GMT+08:00 2019.
    -->
    select 
    <include refid="Base_Column_List" />
    from T_SYSTEM_ROUTE
    where id = #{id,jdbcType=INTEGER}
  </select>
  <delete id="deleteByPrimaryKey" parameterType="java.lang.Integer">
    <!--
      WARNING - @mbg.generated
      This element is automatically generated by MyBatis Generator, do not modify.
      This element was generated on Wed Nov 13 05:06:51 GMT+08:00 2019.
    -->
    delete from T_SYSTEM_ROUTE
    where id = #{id,jdbcType=INTEGER}
  </delete>
  <delete id="deleteByExample" parameterType="com.bird.model.entity.SystemRouteExample">
    <!--
      WARNING - @mbg.generated
      This element is automatically generated by MyBatis Generator, do not modify.
      This element was generated on Wed Nov 13 05:06:51 GMT+08:00 2019.
    -->
    delete from T_SYSTEM_ROUTE
    <if test="_parameter != null">
      <include refid="Example_Where_Clause" />
    </if>
  </delete>
  <insert id="insert" parameterType="com.bird.model.entity.SystemRoute">
    <!--
      WARNING - @mbg.generated
      This element is automatically generated by MyBatis Generator, do not modify.
      This element was generated on Wed Nov 13 05:06:51 GMT+08:00 2019.
    -->
    insert into T_SYSTEM_ROUTE (id, path, parent, 
      async, des)
    values (#{id,jdbcType=INTEGER}, #{path,jdbcType=VARCHAR}, #{parent,jdbcType=INTEGER}, 
      #{async,jdbcType=BIT}, #{des,jdbcType=VARCHAR})
  </insert>
  <insert id="insertSelective" parameterType="com.bird.model.entity.SystemRoute">
    <!--
      WARNING - @mbg.generated
      This element is automatically generated by MyBatis Generator, do not modify.
      This element was generated on Wed Nov 13 05:06:51 GMT+08:00 2019.
    -->
    insert into T_SYSTEM_ROUTE
    <trim prefix="(" suffix=")" suffixOverrides=",">
      <if test="id != null">
        id,
      </if>
      <if test="path != null">
        path,
      </if>
      <if test="parent != null">
        parent,
      </if>
      <if test="async != null">
        async,
      </if>
      <if test="des != null">
        des,
      </if>
    </trim>
    <trim prefix="values (" suffix=")" suffixOverrides=",">
      <if test="id != null">
        #{id,jdbcType=INTEGER},
      </if>
      <if test="path != null">
        #{path,jdbcType=VARCHAR},
      </if>
      <if test="parent != null">
        #{parent,jdbcType=INTEGER},
      </if>
      <if test="async != null">
        #{async,jdbcType=BIT},
      </if>
      <if test="des != null">
        #{des,jdbcType=VARCHAR},
      </if>
    </trim>
  </insert>
  <select id="countByExample" parameterType="com.bird.model.entity.SystemRouteExample" resultType="java.lang.Long">
    <!--
      WARNING - @mbg.generated
      This element is automatically generated by MyBatis Generator, do not modify.
      This element was generated on Wed Nov 13 05:06:51 GMT+08:00 2019.
    -->
    select count(*) from T_SYSTEM_ROUTE
    <if test="_parameter != null">
      <include refid="Example_Where_Clause" />
    </if>
  </select>
  <update id="updateByExampleSelective" parameterType="map">
    <!--
      WARNING - @mbg.generated
      This element is automatically generated by MyBatis Generator, do not modify.
      This element was generated on Wed Nov 13 05:06:51 GMT+08:00 2019.
    -->
    update T_SYSTEM_ROUTE
    <set>
      <if test="record.id != null">
        id = #{record.id,jdbcType=INTEGER},
      </if>
      <if test="record.path != null">
        path = #{record.path,jdbcType=VARCHAR},
      </if>
      <if test="record.parent != null">
        parent = #{record.parent,jdbcType=INTEGER},
      </if>
      <if test="record.async != null">
        async = #{record.async,jdbcType=BIT},
      </if>
      <if test="record.des != null">
        des = #{record.des,jdbcType=VARCHAR},
      </if>
    </set>
    <if test="_parameter != null">
      <include refid="Update_By_Example_Where_Clause" />
    </if>
  </update>
  <update id="updateByExample" parameterType="map">
    <!--
      WARNING - @mbg.generated
      This element is automatically generated by MyBatis Generator, do not modify.
      This element was generated on Wed Nov 13 05:06:51 GMT+08:00 2019.
    -->
    update T_SYSTEM_ROUTE
    set id = #{record.id,jdbcType=INTEGER},
      path = #{record.path,jdbcType=VARCHAR},
      parent = #{record.parent,jdbcType=INTEGER},
      async = #{record.async,jdbcType=BIT},
      des = #{record.des,jdbcType=VARCHAR}
    <if test="_parameter != null">
      <include refid="Update_By_Example_Where_Clause" />
    </if>
  </update>
  <update id="updateByPrimaryKeySelective" parameterType="com.bird.model.entity.SystemRoute">
    <!--
      WARNING - @mbg.generated
      This element is automatically generated by MyBatis Generator, do not modify.
      This element was generated on Wed Nov 13 05:06:51 GMT+08:00 2019.
    -->
    update T_SYSTEM_ROUTE
    <set>
      <if test="path != null">
        path = #{path,jdbcType=VARCHAR},
      </if>
      <if test="parent != null">
        parent = #{parent,jdbcType=INTEGER},
      </if>
      <if test="async != null">
        async = #{async,jdbcType=BIT},
      </if>
      <if test="des != null">
        des = #{des,jdbcType=VARCHAR},
      </if>
    </set>
    where id = #{id,jdbcType=INTEGER}
  </update>
  <update id="updateByPrimaryKey" parameterType="com.bird.model.entity.SystemRoute">
    <!--
      WARNING - @mbg.generated
      This element is automatically generated by MyBatis Generator, do not modify.
      This element was generated on Wed Nov 13 05:06:51 GMT+08:00 2019.
    -->
    update T_SYSTEM_ROUTE
    set path = #{path,jdbcType=VARCHAR},
      parent = #{parent,jdbcType=INTEGER},
      async = #{async,jdbcType=BIT},
      des = #{des,jdbcType=VARCHAR}
    where id = #{id,jdbcType=INTEGER}
  </update>
</mapper>